ts_pygame_engine/coordinates/__init__.py
ts_pygame_engine/coordinates/limited_moving_coordinate.py
ts_pygame_engine/coordinates/moving_coordinate.py
ts_pygame_engine/coordinates/slowing_coordinate.py
ts_pygame_engine/core/__init__.py
ts_pygame_engine/core/drawer.py
ts_pygame_engine/core/game.py
ts_pygame_engine/core/main.py
ts_pygame_engine/core/settings.py
ts_pygame_engine/core/events/__init__.py
ts_pygame_engine/core/events/input.py
ts_pygame_engine/core/events/keyboard.py
ts_pygame_engine/core/events/mouse.py
ts_pygame_engine/primitives/__init__.py
ts_pygame_engine/primitives/vector.py
ts_pygame_engine/ui/__init__.py
ts_pygame_engine/ui/colors.py
ts_pygame_engine/ui/text.py
ts_pygame_engine/ui/containers/__init__.py
ts_pygame_engine/ui/core/__init__.py
ts_pygame_engine/ui/core/container.py
ts_pygame_engine/ui/core/screen.py
ts_pygame_engine/ui/core/widget.py
ts_pygame_engine-1.0.5.dist-info/LICENCE
ts_pygame_engine-1.0.5.dist-info/METADATA
ts_pygame_engine-1.0.5.dist-info/WHEEL
ts_pygame_engine-1.0.5.dist-info/top_level.txt
ts_pygame_engine-1.0.5.dist-info/RECORD
